{
  "returnObj": {
    "result": [
      {
        "fuid": "5c9744ca-f3b6-11ec-ad4e-00505689ac50",
        "targetRegionID": "22f08348-ebbf-11ec-b70d-00505689ac50",
        "targetRegionIDv2": "xxxxxxxxxx8601edba5k024bacxxxxxx",
        "targetRegionName": "xx公有云",
        "targetBucket": "bucket-324d",
        "prefixes": ["nn_", "mm_"],
        "plot": true,
        "history": true,
        "progress": 10.0,
        "lastUpdate": "2022-06-26T10:57:32Z"
      }
    ],
    "currentCount": 1,
    "totalCount": 1
  },
  "message": "SUCCESS",
  "description": "成功",
  "statusCode": 800
}
