{
  "tables": {
    "ecs.instance.list": {
      "row_path": "returnObj.results",
      "columns": [
        {
          "key": "instance_id",
          "path": "instanceID",
          "labels": {
            "zh-CN": "实例ID",
            "en-US": "Instance ID",
            "en-GB": "Instance ID"
          }
        },
        {
          "key": "name",
          "path": "displayName",
          "labels": {
            "zh-CN": "名称",
            "en-US": "Name",
            "en-GB": "Name"
          }
        },
        {
          "key": "status",
          "path": "instanceStatus",
          "labels": {
            "zh-CN": "状态",
            "en-US": "Status",
            "en-GB": "Status"
          }
        },
        {
          "key": "private_ip",
          "path": "privateIP",
          "labels": {
            "zh-CN": "私有IP",
            "en-US": "Private IP",
            "en-GB": "Private IP"
          }
        }
      ]
    },
    "ecs.instance.show": {
      "row_path": "returnObj",
      "columns": [
        {
          "key": "instance_id",
          "path": "instanceID",
          "labels": {
            "zh-CN": "实例ID",
            "en-US": "Instance ID",
            "en-GB": "Instance ID"
          }
        },
        {
          "key": "name",
          "path": "displayName",
          "labels": {
            "zh-CN": "名称",
            "en-US": "Name",
            "en-GB": "Name"
          }
        },
        {
          "key": "status",
          "path": "instanceStatus",
          "labels": {
            "zh-CN": "状态",
            "en-US": "Status",
            "en-GB": "Status"
          }
        },
        {
          "key": "private_ip",
          "path": "privateIP",
          "labels": {
            "zh-CN": "私有IP",
            "en-US": "Private IP",
            "en-GB": "Private IP"
          }
        }
      ]
    },
    "ecs.instance.job": {
      "row_path": "returnObj.jobs",
      "columns": [
        {
          "key": "job_id",
          "path": "jobID",
          "labels": {
            "zh-CN": "任务ID",
            "en-US": "Job ID",
            "en-GB": "Job ID"
          }
        }
      ]
    }
  }
}
