{
  "returnObj": {
    "scalingGroups": [
      {
        "vpcName": "vpc-8fd8",
        "zabbixName": "scal_bac_faa34bbc5d574da7aeb2db096d106bf8_540",
        "subnetList": [
          {
            "az1": ["subnet-9fr7iesyyp"]
          }
        ],
        "subnetIDList": ["subnet-9fr7iesyyp"],
        "minCount": 0,
        "expectedCount": 1,
        "configName": "qyj-config-test-005",
        "healthPeriod": 600,
        "createDate": "2022-10-14 16:32:30",
        "regionID": "81f7728662dd11ec810800155d307d5b",
        "configID": 459,
        "projectIDEcs": "0",
        "healthMode": 1,
        "status": 2,
        "instanceCount": 0,
        "moveOutStrategy": 1,
        "recoveryMode": 2,
        "securityGroupIDList": ["sg-q7v82a1m48"],
        "vpcID": "vpc-a06t51wr1h",
        "maxCount": 50,
        "name": "as-group-3bfc",
        "useLb": 2,
        "vpcCidr": "192.168.0.0/16",
        "updateDate": "2022-10-24 15:35:06",
        "groupID": 540,
        "configList": [459],
        "azStrategy": 1,
        "deleteProtection": false
      }
    ],
    "numberOfAll": 19,
    "totalCount": 1
  },
  "errorCode": "",
  "message": "SUCCESS",
  "description": "成功",
  "statusCode": 800
}
