{
  "returnObj": {
    "images": [
      {
        "appVersion": null,
        "architecture": "x86_64",
        "azName": null,
        "bootMode": "bios",
        "chargeableImage": false,
        "containerFormat": null,
        "createdTime": 1698145871,
        "createdTimeStr": "2023-10-24T11:11:11Z",
        "cwaiType": null,
        "description": "Test CTyunOS",
        "destinationAccountID": "8888f88ee8888fddbdb888bef888e8fe",
        "destinationUser": "test@test.com",
        "diskFormat": null,
        "diskID": null,
        "diskSize": 40,
        "enableImageIntegrityCheck": false,
        "fullECSDiskSize": null,
        "gpuImageCategory": null,
        "hasAcceptedSharedImages": null,
        "imageClass": "ECS",
        "imageDisplayName": null,
        "imageID": "8d8e8888-8ed8-88b8-88cb-888f8b8cf8fa",
        "imageIntegrityCheckStatus": null,
        "imageName": "CTyunOS-test",
        "imageScene": null,
        "imageShareCount": null,
        "imageSize": null,
        "imageSource": "cloud_server",
        "imageStatus": "waiting",
        "imageSubcategory": null,
        "imageType": null,
        "imageVisibility": "shared",
        "maximumRAM": 0,
        "minimumRAM": 0,
        "osDistro": "CTyunOS",
        "osType": "linux",
        "osVersion": "23.01",
        "projectID": null,
        "sourceAccountID": "a88fc8888a8a8b8e8f8888888d888ed8",
        "sourceServerID": null,
        "sourceUser": "ims-test@test.com",
        "supportOneClickSFSMount": false,
        "supportXSSD": false,
        "taskID": null,
        "updatedTime": 1698145871,
        "updatedTimeStr": "2023-10-24T11:11:11Z"
      }
    ],
    "currentPage": 1,
    "pageNo": 1,
    "currentCount": 1,
    "pageSize": 1,
    "totalPage": 1,
    "totalCount": 1
  },
  "errorCode": "",
  "message": "SUCCESS",
  "description": "成功",
  "statusCode": 800
}
